gemini_public_api/__init__.py
gemini_public_api/aiohttp/__init__.py
gemini_public_api/aiohttp/api.py
gemini_public_api/aiohttp/session_context_manager.py
gemini_public_api/api.py
gemini_public_api/public_endpoints.py
gemini_public_api/public_sandbox_endpoints.py
gemini_public_api-0.11.3.dist-info/LICENSE
gemini_public_api-0.11.3.dist-info/METADATA
gemini_public_api-0.11.3.dist-info/WHEEL
gemini_public_api-0.11.3.dist-info/RECORD
