Metadata-Version: 2.3
Name: gemini-public-api
Version: 0.11.3
Summary: ⚠️ This package is no longer maintained. No future updates will be released.
Author: Michal Polit
Author-email: mpolit@protonmail.com
Requires-Python: >=3.9,<4.0
Classifier: Development Status :: 7 - Inactive
Classifier: License :: OSI Approved :: MIT License
Classifier: Operating System :: OS Independent
Classifier: Programming Language :: Python :: 3
Classifier: Programming Language :: Python :: 3.9
Classifier: Programming Language :: Python :: 3.10
Classifier: Programming Language :: Python :: 3.11
Classifier: Programming Language :: Python :: 3.12
Classifier: Programming Language :: Python :: 3.13
Requires-Dist: aiohttp (>=3.9.3,<4.0.0)
Requires-Dist: certifi (==2025.6.15)
Requires-Dist: charset-normalizer (==3.4.2)
Requires-Dist: idna (==3.10)
Requires-Dist: requests (>=2.31.0,<3.0.0)
Requires-Dist: urllib3 (==2.5.0)
